LICENSE
MANIFEST.in
README.rst
setup.py
django_lithium_api/__init__.py
django_lithium_api/api.py
django_lithium_api/enums.py
django_lithium_api/exceptions.py
django_lithium_api/settings.py
django_lithium_api/signals.py
django_lithium_api/tests.py
django_lithium_api/types.py
django_lithium_api/views.py
django_lithium_api.egg-info/PKG-INFO
django_lithium_api.egg-info/SOURCES.txt
django_lithium_api.egg-info/dependency_links.txt
django_lithium_api.egg-info/not-zip-safe
django_lithium_api.egg-info/requires.txt
django_lithium_api.egg-info/top_level.txt
django_lithium_api/management/__init__.py
django_lithium_api/management/commands/__init__.py
django_lithium_api/management/commands/_utils.py
django_lithium_api/management/commands/lithium_events.py
django_lithium_api/management/commands/lithium_import.py