Metadata-Version: 1.1
Name: django-lithium-api
Version: 0.1.5
Summary: A (very) limited implementation of the Lithium REST API for Django
Home-page: https://github.com/piquadrat/django-lithium-api
Author: Benjamin Wohlwend
Author-email: piquadrat@gmail.com
License: UNKNOWN
Platform: UNKNOWN
Classifier: Development Status :: 3 - Alpha
Classifier: Framework :: Django
Classifier: Intended Audience :: Developers
Classifier: License :: OSI Approved :: BSD License
Classifier: Operating System :: OS Independent
Classifier: Programming Language :: Python :: 2.6
Classifier: Programming Language :: Python :: 2.7
Classifier: Topic :: Internet :: WWW/HTTP :: Dynamic Content
